hiddenlayer/__init__.py
hiddenlayer/canvas.py
hiddenlayer/ge.py
hiddenlayer/graph.py
hiddenlayer/history.py
hiddenlayer/pytorch_builder.py
hiddenlayer/tf_builder.py
hiddenlayer/transforms.py
hiddenlayer/utils.py
hiddenlayer-0.3.dist-info/LICENSE
hiddenlayer-0.3.dist-info/METADATA
hiddenlayer-0.3.dist-info/WHEEL
hiddenlayer-0.3.dist-info/top_level.txt
hiddenlayer-0.3.dist-info/RECORD
